munidata/__init__.py
munidata/database.py
munidata/manager.py
munidata/idna/__init__.py
munidata/idna/idna_tables_1000.py
munidata/idna/idna_tables_520.py
munidata/idna/idna_tables_600.py
munidata/idna/idna_tables_610.py
munidata/idna/idna_tables_620.py
munidata/idna/idna_tables_630.py
munidata/idna/idna_tables_700.py
munidata/idna/idna_tables_800.py
munidata/idna/idna_tables_900.py
munidata/idna/idnatables.py
munidata-2.0.0.data/scripts/parse_idna_tables.py
munidata-2.0.0.dist-info/METADATA
munidata-2.0.0.dist-info/RECORD
munidata-2.0.0.dist-info/WHEEL
munidata-2.0.0.dist-info/top_level.txt
