Metadata-Version: 2.1
Name: munidata
Version: 2.0.0
Summary: Provides an API for accessing multiple instances of Unicode data
Home-page: UNKNOWN
Author: Viagenie and Wil Tan
Author-email: support@viagenie.ca
License: TBD
Platform: UNKNOWN
Classifier: Operating System :: OS Independent
Classifier: Programming Language :: Python
Classifier: Programming Language :: Python :: 2.7
Classifier: Programming Language :: Python :: 3.4
Classifier: Programming Language :: Python :: 3.5
Classifier: Programming Language :: Python :: 3.6
Classifier: Topic :: Software Development :: Libraries
Requires-Dist: picu
